paddle_webhook_signature_verifier.py
paddle_webhook_signature_verifier-1.0.2.dist-info/LICENSE
paddle_webhook_signature_verifier-1.0.2.dist-info/METADATA
paddle_webhook_signature_verifier-1.0.2.dist-info/WHEEL
paddle_webhook_signature_verifier-1.0.2.dist-info/top_level.txt
paddle_webhook_signature_verifier-1.0.2.dist-info/RECORD
