Metadata-Version: 2.1
Name: paddle-webhook-signature-verifier
Version: 1.0.2
Summary: A Python package for verifying Paddle webhook signature
Home-page: https://github.com/afterword-tech/paddle_webhook_signature_verifier
Author: Aneesh Arora
Author-email: aneesh.arora.aa@gmail.com
Classifier: Programming Language :: Python :: 3
Classifier: License :: OSI Approved :: MIT License
Classifier: Operating System :: OS Independent
Requires-Python: >=3.6
License-File: LICENSE
